contracts/__about__.py
contracts/__init__.py
contracts/address.py
contracts/application.py
contracts/message.py
contracts/operation.py
contracts/testing.py
contracts/types.py
contracts/backends/micro/__init__.py
contracts/backends/micro/micro.py
contracts/interfaces/__init__.py
contracts/interfaces/client.py
contracts/interfaces/server.py
contracts/specification/__init__.py
contracts/specification/asyncapi.py
contracts/specification/builder.py
contracts/specification/renderer.py
contracts/validation/__init__.py
contracts/validation/interface.py
contracts/validation/pydantic_v1.py
contracts/validation/pydantic_v2.py
contracts/validation/standard.py
asyncapi_contracts-0.0.2.dev0.dist-info/METADATA
asyncapi_contracts-0.0.2.dev0.dist-info/WHEEL
asyncapi_contracts-0.0.2.dev0.dist-info/RECORD
