Metadata-Version: 2.1
Name: asyncapi-contracts
Version: 0.0.2.dev0
Summary: Contract driven development of Async API applications in Python
Author-email: Guillaume Charbonnier <guillaume.charbonnier@araymond.com>
License: MIT
Requires-Python: >=3.8
Requires-Dist: nats-micro
Requires-Dist: pydantic>=1
Requires-Dist: starlette
Requires-Dist: typing-extensions
Requires-Dist: uvicorn
